{"name":"數位影像處理課程","tagline":"台北科大資訊工程系 多媒體資訊與技術整合實驗室","body":"## 數位影像處理 HW2\r\n\r\n![視窗畫面](http://i.imgur.com/bKzG0kK.png)\r\n\r\n\r\n<iframe width=\"640\" height=\"480\" src=\"http://www.youtube-nocookie.com/embed/RavZvuspQks?rel=0\" frameborder=\"0\" allowfullscreen></iframe>\r\n\r\n### 作業需求\r\n\r\n***\r\n\r\n本次作業目的為使用 **OpenCV 程式庫** 擷取即時影像輸入(如：Webcam)對其進行影像處理應用， **範例專案** 將提供Webcam輸入\r\n選取物件開始進行 Camshift 物件追蹤功能。\r\n\r\n各式應用請各位同學們發揮創意與想像力完成並在繳交期限內完成實作並上傳，有任何問題請與助教聯絡。\r\n\r\n\r\n#### 應用範例\r\n滑鼠控制, 電流急急棒, 接球遊戲...等等\r\n\r\n### 執行環境\r\n\r\n***\r\n\r\n[範例專案下載](https://github.com/imZack/Digital-Image-Processing-2/zipball/master)\r\n\r\n[http://ppt.cc/-qPD](http://ppt.cc/-qPD)\r\n\r\n### 執行環境\r\n\r\n***\r\n範例專案使用 Microsoft Visual Studio 2010 C#\r\n\r\n使用 Emgu(www.emgu.com) 程式庫 (OpenCV 在 C# 下的封裝)\r\n\r\n如想使用其他方式/語言撰寫，請依照範例專案內的功能與介面操作方式呈現\r\n\r\n### 繳交時間\r\n\r\n***\r\n\r\n**2013/6/21 星期五**\r\n\r\n### 上傳方式\r\n\r\n***\r\n\r\n請刪除 `{project_dir}\\bin` 其餘檔案打包壓縮成 ZIP 格式 \r\n\r\n**命名規則** 請務必遵守 `hw2_學號.zip` \r\n\r\n上傳至 `ftp://ftp.mitlab.org` \r\n\r\n帳號 `dip_upload` 密碼 `mitlab1621!`\r\n\r\n上傳後即不得刪除覆蓋，如需更新檔案請更改名稱為 `hw2_學號_2.zip` 依此類推\r\n\r\n\r\n### 助教聯絡方式\r\n\r\n***\r\n\r\n如果對於作業有不懂或是遇到困難的地方，請盡速與助教聯繫。  \r\n**LAB 1621** 施宇倫  <t100598029@ntut.org.tw>\r\n\r\n02-27712171 ext. 4269\r\n\r\n**程式碼嚴禁抄襲**","google":"UA-5959305-11","note":"Don't delete this file! It's used internally to help with page regeneration."}